lttnganalyses/__init__.py
lttnganalyses/_version.py
lttnganalyses/cli/__init__.py
lttnganalyses/cli/command.py
lttnganalyses/cli/cputop.py
lttnganalyses/cli/io.py
lttnganalyses/cli/irq.py
lttnganalyses/cli/memtop.py
lttnganalyses/cli/mi.py
lttnganalyses/cli/period_parsing.py
lttnganalyses/cli/periods.py
lttnganalyses/cli/progressbar.py
lttnganalyses/cli/sched.py
lttnganalyses/cli/syscallstats.py
lttnganalyses/cli/termgraph.py
lttnganalyses/common/__init__.py
lttnganalyses/common/format_utils.py
lttnganalyses/common/parse_utils.py
lttnganalyses/common/time_utils.py
lttnganalyses/common/trace_utils.py
lttnganalyses/common/version_utils.py
lttnganalyses/core/__init__.py
lttnganalyses/core/analysis.py
lttnganalyses/core/cputop.py
lttnganalyses/core/event.py
lttnganalyses/core/io.py
lttnganalyses/core/irq.py
lttnganalyses/core/memtop.py
lttnganalyses/core/period.py
lttnganalyses/core/periods.py
lttnganalyses/core/sched.py
lttnganalyses/core/stats.py
lttnganalyses/core/syscalls.py
lttnganalyses/linuxautomaton/__init__.py
lttnganalyses/linuxautomaton/automaton.py
lttnganalyses/linuxautomaton/block.py
lttnganalyses/linuxautomaton/io.py
lttnganalyses/linuxautomaton/irq.py
lttnganalyses/linuxautomaton/mem.py
lttnganalyses/linuxautomaton/net.py
lttnganalyses/linuxautomaton/sched.py
lttnganalyses/linuxautomaton/sp.py
lttnganalyses/linuxautomaton/statedump.py
lttnganalyses/linuxautomaton/sv.py
lttnganalyses/linuxautomaton/syscalls.py
lttnganalyses-0.6.1.data/scripts/lttng-analyses-record
lttnganalyses-0.6.1.data/scripts/lttng-track-process
lttnganalyses-0.6.1.dist-info/DESCRIPTION.rst
lttnganalyses-0.6.1.dist-info/METADATA
lttnganalyses-0.6.1.dist-info/RECORD
lttnganalyses-0.6.1.dist-info/WHEEL
lttnganalyses-0.6.1.dist-info/entry_points.txt
lttnganalyses-0.6.1.dist-info/metadata.json
lttnganalyses-0.6.1.dist-info/top_level.txt
