Metadata-Version: 2.0
Name: lttnganalyses
Version: 0.6.1
Summary: LTTng analyses
Home-page: https://github.com/lttng/lttng-analyses
Author: Julien Desfossez
Author-email: jdesfossez@efficios.com
License: MIT
Keywords: lttng tracing
Platform: UNKNOWN
Classifier: Development Status :: 4 - Beta
Classifier: Intended Audience :: Developers
Classifier: Intended Audience :: System Administrators
Classifier: Topic :: System :: Monitoring
Classifier: License :: OSI Approved :: MIT License
Classifier: Programming Language :: Python :: 3.4
Requires-Dist: pyparsing
Provides-Extra: progressbar
Requires-Dist: progressbar; extra == 'progressbar'
